{
    "liteAttributesSet" : "hc_id,hc_name,hc_alias,hc_activate",
    "repository" : "\\CentreonConfiguration\\Repository\\HostcategoryRepository",
    "objectBaseUrl" : "hostcategory",
    "objectClass" : "\\CentreonConfiguration\\Models\\Hostcategory",
    "relationMap" : {
        "host" : "\\CentreonConfiguration\\Models\\Relation\\Host\\Hostcategory",
        "hosttemplate" : "\\CentreonConfiguration\\Models\\Relation\\Hosttemplate\\Hostcategory"
    },
    "attributesMap" : {
        "id" : "hc_id",
        "name" : "hc_name",
        "description" : "hc_alias",
        "status" : "hc_activate"
    }
}
