{
    "liteAttributesSet" : "id,name,description,command_line,enabled",
    "repository" : "\\CentreonConfiguration\\Repository\\ConnectorRepository",
    "objectBaseUrl" : "connector",
    "objectClass" : "\\CentreonConfiguration\\Models\\Connector",
    "relationMap" : {
        "connector_command": "\\CentreonConfiguration\\Models\\Relation\\Connector\\Command"
    },
    "attributesMap" : {
        "id" : "id",
        "name" : "name",
        "description" : "description",
        "command line" : "connector_line",
        "activate" : "enabled"
    },
    "options" : {
        "showAction" : {
            "connector" : {
              "functionParams" : "object",
              "help": "The connector",
              "type": "string",
              "toTransform" : "connector",
              "multiple" : false,
              "required" : true
            }
        },
        "createAction" : {
            
        },
        "updateAction" : {
            "connector" : {
              "functionParams" : "object",
              "help": "The connector",
              "type": "string",
              "toTransform" : "connector",
              "multiple" : false,
              "required" : true
            }
        },
        "deleteAction" : {
            "connector" : {
              "functionParams" : "object",
              "help": "The connector",
              "type": "string",
              "toTransform" : "connector",
              "multiple" : false,
              "required" : true
            }
        },
        "duplicateAction" : {
            "connector" : {
              "functionParams" : "object",
              "help": "The connector",
              "type": "string",
              "toTransform" : "connector",
              "multiple" : false,
              "required" : true
            }
        }
    }
}
